lumaai/__init__.py
lumaai/_base_client.py
lumaai/_client.py
lumaai/_compat.py
lumaai/_constants.py
lumaai/_exceptions.py
lumaai/_files.py
lumaai/_models.py
lumaai/_qs.py
lumaai/_resource.py
lumaai/_response.py
lumaai/_streaming.py
lumaai/_types.py
lumaai/_version.py
lumaai/py.typed
lumaai/_utils/__init__.py
lumaai/_utils/_compat.py
lumaai/_utils/_datetime_parse.py
lumaai/_utils/_logs.py
lumaai/_utils/_proxy.py
lumaai/_utils/_reflection.py
lumaai/_utils/_resources_proxy.py
lumaai/_utils/_streams.py
lumaai/_utils/_sync.py
lumaai/_utils/_transform.py
lumaai/_utils/_typing.py
lumaai/_utils/_utils.py
lumaai/lib/.keep
lumaai/resources/__init__.py
lumaai/resources/credits.py
lumaai/resources/ping.py
lumaai/resources/generations/__init__.py
lumaai/resources/generations/concepts.py
lumaai/resources/generations/generations.py
lumaai/resources/generations/image.py
lumaai/resources/generations/video.py
lumaai/types/__init__.py
lumaai/types/credit_get_response.py
lumaai/types/generation.py
lumaai/types/generation_audio_params.py
lumaai/types/generation_create_params.py
lumaai/types/generation_list_params.py
lumaai/types/generation_list_response.py
lumaai/types/generation_upscale_params.py
lumaai/types/ping_check_response.py
lumaai/types/generations/__init__.py
lumaai/types/generations/concept_list_response.py
lumaai/types/generations/image_create_params.py
lumaai/types/generations/image_reframe_params.py
lumaai/types/generations/video_create_params.py
lumaai/types/generations/video_modify_params.py
lumaai/types/generations/video_reframe_params.py
lumaai-1.19.1.dist-info/METADATA
lumaai-1.19.1.dist-info/WHEEL
lumaai-1.19.1.dist-info/licenses/LICENSE
lumaai-1.19.1.dist-info/RECORD
